LICENSE
MANIFEST.in
setup.cfg
setup.py
py_eve_chat_mon/__init__.py
py_eve_chat_mon/chat_directory.py
py_eve_chat_mon/chat_message.py
py_eve_chat_mon/exceptions.py
py_eve_chat_mon/monitor.py
py_eve_chat_mon.egg-info/PKG-INFO
py_eve_chat_mon.egg-info/SOURCES.txt
py_eve_chat_mon.egg-info/dependency_links.txt
py_eve_chat_mon.egg-info/requires.txt
py_eve_chat_mon.egg-info/top_level.txt