Metadata-Version: 1.1
Name: py-eve-chat-mon
Version: 0.5
Summary: A library that focuses on monitoring EVE Online chat logs for messages and doing nothing else. It is meant to be focused and lightweight.
Home-page: https://github.com/andrewpmartinez/py-eve-chat-mon
Author: Andrew Martinez
Author-email: andrew.p.martinez@gmail.com
License: MIT
Download-URL: https://github.com/andrewpmartinez/py-eve-chat-mon/tarball/0.
Keywords: EVE chat monitor
Platform: UNKNOWN
Classifier: Development Status :: 5 - Production/Stable
Classifier: License :: OSI Approved :: MIT License
Classifier: Natural Language :: English
Classifier: Programming Language :: Python :: 3 :: Only
Classifier: Topic :: Software Development :: Libraries
